setup.py
keywrapper/__init__.py
keywrapper/keywrapper.py
keywrapper.egg-info/PKG-INFO
keywrapper.egg-info/SOURCES.txt
keywrapper.egg-info/dependency_links.txt
keywrapper.egg-info/requires.txt
keywrapper.egg-info/top_level.txt
keywrapper.egg-info/zip-safe