Metadata-Version: 1.0
Name: keywrapper
Version: 0.1.0
Summary: Extremely simple key-value storage wrapper
Home-page: https://github.com/lbosque/keywrapper
Author: Luis Bosque
Author-email: luisico@gmai.com
License: BSD-3
Platform: UNKNOWN
